videocloud/__init__.py
videocloud/gui.py
videocloud/main.py
videocloud/assets/cloud.png
videocloud/assets/font/NotoSans.ttf
videocloud-3.0.0.dist-info/LICENSE
videocloud-3.0.0.dist-info/METADATA
videocloud-3.0.0.dist-info/WHEEL
videocloud-3.0.0.dist-info/entry_points.txt
videocloud-3.0.0.dist-info/top_level.txt
videocloud-3.0.0.dist-info/RECORD
