Metadata-Version: 2.1
Name: videocloud
Version: 3.0.0
Summary: A command line tool that generates word clouds from YouTube video captions
Home-page: https://github.com/paramt/VideoCloud
Author: Param Thakkar
Author-email: contact@param.me
License: MIT
Platform: UNKNOWN
Requires-Python: >= 3.6
Requires-Dist: pillow (==6.1.0)
Requires-Dist: wordcloud (==1.5.0)
Requires-Dist: youtube-transcript-api (==0.1.5)
Requires-Dist: numpy (==1.16.4)
Requires-Dist: click (==7.0)
